html2eml/__init__.py
html2eml/html2eml.py
html2eml-0.0.5.dist-info/LICENSE
html2eml-0.0.5.dist-info/METADATA
html2eml-0.0.5.dist-info/WHEEL
html2eml-0.0.5.dist-info/top_level.txt
html2eml-0.0.5.dist-info/RECORD
