Metadata-Version: 2.1
Name: html2eml
Version: 0.0.5
Summary: html2eml is a simple package for converting HTML text to EML format (MIME RFC 2822)
Home-page: https://github.com/gaijinx/html2eml
Author: Konrad Gadzina
Author-email: konradgadzina@gmail.com
License: MIT
Download-URL: https://pypi.org/project/html2eml/
Keywords: EML,HTML,Email,MIME,Multipart
Platform: UNKNOWN
